{
  "__inputs": [
    {
      "name": "DS_PROMETHEUS",
      "label": "Prometheus",
      "description": "",
      "type": "datasource",
      "pluginId": "prometheus",
      "pluginName": "Prometheus"
    }
  ],
  "__requires": [
    {
      "type": "grafana",
      "id": "grafana",
      "name": "Grafana",
      "version": "8.1.0"
    },
    {
      "type": "panel",
      "id": "heatmap",
      "name": "Heatmap",
      "version": ""
    },
    {
      "type": "datasource",
      "id": "prometheus",
      "name": "Prometheus",
      "version": "1.0.0"
    },
    {
      "type": "panel",
      "id": "timeseries",
      "name": "Time series",
      "version": ""
    }
  ],
  "annotations": {
    "list": [
      {
        "builtIn": 1,
        "datasource": "-- Grafana --",
        "enable": true,
        "hide": true,
        "iconColor": "rgba(0, 211, 255, 1)",
        "name": "Annotations & Alerts",
        "target": {
          "limit": 100,
          "matchAny": false,
          "tags": [],
          "type": "dashboard"
        },
        "type": "dashboard"
      }
    ]
  },
  "description": "",
  "editable": true,
  "gnetId": null,
  "graphTooltip": 1,
  "id": null,
  "iteration": 1629455457902,
  "links": [],
  "panels": [
    {
      "datasource": "${DS_PROMETHEUS}",
      "fieldConfig": {
        "defaults": {
          "color": {
            "mode": "palette-classic"
          },
          "custom": {
            "axisLabel": "",
            "axisPlacement": "auto",
            "barAlignment": 0,
            "drawStyle": "line",
            "fillOpacity": 10,
            "gradientMode": "none",
            "hideFrom": {
              "legend": false,
              "tooltip": false,
              "viz": false
            },
            "lineInterpolation": "linear",
            "lineWidth": 1,
            "pointSize": 5,
            "scaleDistribution": {
              "type": "linear"
            },
            "showPoints": "never",
            "spanNulls": true,
            "stacking": {
              "group": "A",
              "mode": "none"
            },
            "thresholdsStyle": {
              "mode": "off"
            }
          },
          "mappings": [],
          "thresholds": {
            "mode": "absolute",
            "steps": [
              {
                "color": "green",
                "value": null
              },
              {
                "color": "red",
                "value": 80
              }
            ]
          },
          "unit": "short"
        },
        "overrides": []
      },
      "gridPos": {
        "h": 8,
        "w": 8,
        "x": 0,
        "y": 0
      },
      "id": 2,
      "options": {
        "legend": {
          "calcs": [],
          "displayMode": "list",
          "placement": "bottom"
        },
        "tooltip": {
          "mode": "multi"
        }
      },
      "pluginVersion": "8.1.0",
      "targets": [
        {
          "exemplar": true,
          "expr": "rate(wormhole_eth_current_height{instance=~\"$instance\"}[$__rate_interval])",
          "hide": false,
          "instant": false,
          "interval": "",
          "legendFormat": "{{eth_network}} - {{instance}}",
          "queryType": "randomWalk",
          "refId": "A"
        }
      ],
      "timeFrom": null,
      "timeShift": null,
      "title": "ETH Blocks/s",
      "type": "timeseries"
    },
    {
      "datasource": "${DS_PROMETHEUS}",
      "fieldConfig": {
        "defaults": {
          "color": {
            "mode": "palette-classic"
          },
          "custom": {
            "axisLabel": "",
            "axisPlacement": "auto",
            "barAlignment": 0,
            "drawStyle": "line",
            "fillOpacity": 10,
            "gradientMode": "none",
            "hideFrom": {
              "legend": false,
              "tooltip": false,
              "viz": false
            },
            "lineInterpolation": "linear",
            "lineWidth": 1,
            "pointSize": 5,
            "scaleDistribution": {
              "type": "linear"
            },
            "showPoints": "never",
            "spanNulls": false,
            "stacking": {
              "group": "A",
              "mode": "none"
            },
            "thresholdsStyle": {
              "mode": "off"
            }
          },
          "mappings": [],
          "thresholds": {
            "mode": "absolute",
            "steps": [
              {
                "color": "green",
                "value": null
              },
              {
                "color": "red",
                "value": 80
              }
            ]
          },
          "unit": "short"
        },
        "overrides": []
      },
      "gridPos": {
        "h": 8,
        "w": 8,
        "x": 8,
        "y": 0
      },
      "id": 3,
      "options": {
        "legend": {
          "calcs": [],
          "displayMode": "list",
          "placement": "bottom"
        },
        "tooltip": {
          "mode": "multi"
        }
      },
      "pluginVersion": "8.1.0",
      "targets": [
        {
          "exemplar": true,
          "expr": "rate(wormhole_solana_current_height{instance=~\"$instance\"}[$__rate_interval])",
          "interval": "",
          "legendFormat": "{{commitment}} - {{instance}}",
          "queryType": "randomWalk",
          "refId": "A"
        }
      ],
      "timeFrom": null,
      "timeShift": null,
      "title": "Solana Slots/s",
      "type": "timeseries"
    },
    {
      "datasource": "${DS_PROMETHEUS}",
      "fieldConfig": {
        "defaults": {
          "color": {
            "mode": "palette-classic"
          },
          "custom": {
            "axisLabel": "",
            "axisPlacement": "auto",
            "barAlignment": 0,
            "drawStyle": "line",
            "fillOpacity": 15,
            "gradientMode": "none",
            "hideFrom": {
              "legend": false,
              "tooltip": false,
              "viz": false
            },
            "lineInterpolation": "linear",
            "lineWidth": 1,
            "pointSize": 5,
            "scaleDistribution": {
              "type": "linear"
            },
            "showPoints": "never",
            "spanNulls": true,
            "stacking": {
              "group": "A",
              "mode": "none"
            },
            "thresholdsStyle": {
              "mode": "off"
            }
          },
          "mappings": [],
          "thresholds": {
            "mode": "absolute",
            "steps": [
              {
                "color": "green",
                "value": null
              },
              {
                "color": "red",
                "value": 80
              }
            ]
          },
          "unit": "short"
        },
        "overrides": []
      },
      "gridPos": {
        "h": 8,
        "w": 8,
        "x": 16,
        "y": 0
      },
      "id": 14,
      "options": {
        "legend": {
          "calcs": [],
          "displayMode": "list",
          "placement": "bottom"
        },
        "tooltip": {
          "mode": "multi"
        }
      },
      "pluginVersion": "8.1.0",
      "targets": [
        {
          "exemplar": true,
          "expr": "rate(wormhole_terra_current_height{instance=~\"$instance\"}[$__rate_interval])",
          "interval": "",
          "legendFormat": "{{instance}}",
          "queryType": "randomWalk",
          "refId": "A"
        }
      ],
      "timeFrom": null,
      "timeShift": null,
      "title": "Terra Slots/s",
      "type": "timeseries"
    },
    {
      "datasource": "${DS_PROMETHEUS}",
      "fieldConfig": {
        "defaults": {
          "color": {
            "mode": "palette-classic"
          },
          "custom": {
            "axisLabel": "",
            "axisPlacement": "auto",
            "barAlignment": 0,
            "drawStyle": "line",
            "fillOpacity": 10,
            "gradientMode": "none",
            "hideFrom": {
              "legend": false,
              "tooltip": false,
              "viz": false
            },
            "lineInterpolation": "linear",
            "lineWidth": 1,
            "pointSize": 5,
            "scaleDistribution": {
              "type": "linear"
            },
            "showPoints": "never",
            "spanNulls": false,
            "stacking": {
              "group": "A",
              "mode": "none"
            },
            "thresholdsStyle": {
              "mode": "off"
            }
          },
          "mappings": [],
          "thresholds": {
            "mode": "absolute",
            "steps": [
              {
                "color": "green",
                "value": null
              },
              {
                "color": "red",
                "value": 80
              }
            ]
          },
          "unit": "short"
        },
        "overrides": []
      },
      "gridPos": {
        "h": 8,
        "w": 8,
        "x": 0,
        "y": 8
      },
      "id": 4,
      "options": {
        "legend": {
          "calcs": [],
          "displayMode": "list",
          "placement": "bottom"
        },
        "tooltip": {
          "mode": "single"
        }
      },
      "pluginVersion": "8.1.0",
      "targets": [
        {
          "exemplar": true,
          "expr": "increase(wormhole_aggregation_state_unobserved_total{instance=~\"$instance\"}[$__rate_interval])",
          "interval": "",
          "legendFormat": "unobserved - {{instance}}",
          "queryType": "randomWalk",
          "refId": "A"
        },
        {
          "exemplar": true,
          "expr": "increase(wormhole_aggregation_state_expirations_total{instance=~\"$instance\"}[$__rate_interval])",
          "hide": false,
          "interval": "",
          "legendFormat": "expirations - {{instance}}",
          "refId": "B"
        },
        {
          "exemplar": true,
          "expr": "increase(wormhole_aggregation_state_retries_total{instance=~\"$instance\"}[$__rate_interval])",
          "interval": "",
          "legendFormat": "retries  - {{instance}}",
          "refId": "C"
        },
        {
          "exemplar": true,
          "expr": "sum without (addr, origin, status)(increase(wormhole_aggregation_state_settled_signatures_total{instance=~\"$instance\"}[$__rate_interval]))",
          "interval": "",
          "legendFormat": "settled  - {{instance}}",
          "refId": "D"
        },
        {
          "exemplar": true,
          "expr": "increase(wormhole_aggregation_state_timeout_total{instance=~\"$instance\"}[$__rate_interval])",
          "interval": "",
          "legendFormat": "timeout  - {{instance}}",
          "refId": "E"
        }
      ],
      "timeFrom": null,
      "timeShift": null,
      "title": "Aggregation Cleanup State Machine",
      "type": "timeseries"
    },
    {
      "datasource": "${DS_PROMETHEUS}",
      "fieldConfig": {
        "defaults": {
          "color": {
            "mode": "palette-classic"
          },
          "custom": {
            "axisLabel": "",
            "axisPlacement": "auto",
            "barAlignment": 0,
            "drawStyle": "line",
            "fillOpacity": 51,
            "gradientMode": "none",
            "hideFrom": {
              "legend": false,
              "tooltip": false,
              "viz": false
            },
            "lineInterpolation": "linear",
            "lineWidth": 1,
            "pointSize": 5,
            "scaleDistribution": {
              "type": "linear"
            },
            "showPoints": "never",
            "spanNulls": true,
            "stacking": {
              "group": "A",
              "mode": "none"
            },
            "thresholdsStyle": {
              "mode": "off"
            }
          },
          "mappings": [],
          "thresholds": {
            "mode": "absolute",
            "steps": [
              {
                "color": "green",
                "value": null
              },
              {
                "color": "red",
                "value": 80
              }
            ]
          },
          "unit": "short"
        },
        "overrides": []
      },
      "gridPos": {
        "h": 8,
        "w": 8,
        "x": 8,
        "y": 8
      },
      "id": 6,
      "options": {
        "legend": {
          "calcs": [],
          "displayMode": "list",
          "placement": "bottom"
        },
        "tooltip": {
          "mode": "multi"
        }
      },
      "pluginVersion": "8.1.0",
      "targets": [
        {
          "exemplar": true,
          "expr": "wormhole_aggregation_state_entries{instance=~\"$instance\"}",
          "interval": "",
          "legendFormat": "count - {{instance}}",
          "queryType": "randomWalk",
          "refId": "A"
        }
      ],
      "timeFrom": null,
      "timeShift": null,
      "title": "Aggregation State Size",
      "type": "timeseries"
    },
    {
      "datasource": "${DS_PROMETHEUS}",
      "fieldConfig": {
        "defaults": {
          "color": {
            "mode": "palette-classic"
          },
          "custom": {
            "axisLabel": "",
            "axisPlacement": "auto",
            "barAlignment": 0,
            "drawStyle": "line",
            "fillOpacity": 10,
            "gradientMode": "none",
            "hideFrom": {
              "legend": false,
              "tooltip": false,
              "viz": false
            },
            "lineInterpolation": "linear",
            "lineWidth": 1,
            "pointSize": 5,
            "scaleDistribution": {
              "type": "linear"
            },
            "showPoints": "never",
            "spanNulls": false,
            "stacking": {
              "group": "A",
              "mode": "none"
            },
            "thresholdsStyle": {
              "mode": "off"
            }
          },
          "decimals": 2,
          "mappings": [],
          "thresholds": {
            "mode": "absolute",
            "steps": [
              {
                "color": "green",
                "value": null
              },
              {
                "color": "red",
                "value": 80
              }
            ]
          },
          "unit": "short"
        },
        "overrides": []
      },
      "gridPos": {
        "h": 8,
        "w": 8,
        "x": 16,
        "y": 8
      },
      "id": 7,
      "options": {
        "legend": {
          "calcs": [],
          "displayMode": "list",
          "placement": "bottom"
        },
        "tooltip": {
          "mode": "multi"
        }
      },
      "pluginVersion": "8.1.0",
      "targets": [
        {
          "exemplar": true,
          "expr": "increase(wormhole_eth_lockups_found_total{instance=~\"$instance\"}[$__rate_interval])",
          "interval": "",
          "legendFormat": "ethereum (found) - {{instance}}",
          "queryType": "randomWalk",
          "refId": "A"
        },
        {
          "exemplar": true,
          "expr": "increase(wormhole_eth_lockups_confirmed_total{instance=~\"$instance\"}[$__rate_interval])",
          "interval": "",
          "legendFormat": "ethereum (confirmed) - {{instance}}",
          "queryType": "randomWalk",
          "refId": "B"
        },
        {
          "exemplar": true,
          "expr": "increase(wormhole_solana_lockups_confirmed_total{instance=~\"$instance\"}[$__rate_interval])",
          "interval": "",
          "legendFormat": "solana (confirmed) - {{instance}}",
          "queryType": "randomWalk",
          "refId": "C"
        },
        {
          "exemplar": true,
          "expr": "increase(wormhole_terra_lockups_confirmed_total{instance=~\"$instance\"}[$__rate_interval])",
          "interval": "",
          "legendFormat": "terra (confirmed)  - {{instance}}",
          "queryType": "randomWalk",
          "refId": "D"
        }
      ],
      "timeFrom": null,
      "timeShift": null,
      "title": "Lockup Observations",
      "type": "timeseries"
    },
    {
      "datasource": "${DS_PROMETHEUS}",
      "fieldConfig": {
        "defaults": {
          "color": {
            "mode": "palette-classic"
          },
          "custom": {
            "axisLabel": "",
            "axisPlacement": "auto",
            "barAlignment": 0,
            "drawStyle": "line",
            "fillOpacity": 40,
            "gradientMode": "none",
            "hideFrom": {
              "legend": false,
              "tooltip": false,
              "viz": false
            },
            "lineInterpolation": "linear",
            "lineWidth": 1,
            "pointSize": 5,
            "scaleDistribution": {
              "type": "linear"
            },
            "showPoints": "never",
            "spanNulls": true,
            "stacking": {
              "group": "A",
              "mode": "none"
            },
            "thresholdsStyle": {
              "mode": "off"
            }
          },
          "mappings": [],
          "thresholds": {
            "mode": "absolute",
            "steps": [
              {
                "color": "green",
                "value": null
              },
              {
                "color": "red",
                "value": 80
              }
            ]
          },
          "unit": "short"
        },
        "overrides": []
      },
      "gridPos": {
        "h": 6,
        "w": 12,
        "x": 0,
        "y": 16
      },
      "id": 8,
      "options": {
        "legend": {
          "calcs": [],
          "displayMode": "list",
          "placement": "bottom"
        },
        "tooltip": {
          "mode": "single"
        }
      },
      "pluginVersion": "8.1.0",
      "targets": [
        {
          "exemplar": true,
          "expr": "wormhole_solana_fee_account_balance_lamports{instance=~\"$instance\"}",
          "interval": "",
          "legendFormat": "lamport (1B = 1 SOL) - {{instance}}",
          "queryType": "randomWalk",
          "refId": "A"
        }
      ],
      "timeFrom": null,
      "timeShift": null,
      "title": "Solana Fee Payer Balance",
      "type": "timeseries"
    },
    {
      "datasource": "${DS_PROMETHEUS}",
      "fieldConfig": {
        "defaults": {
          "color": {
            "mode": "palette-classic"
          },
          "custom": {
            "axisLabel": "",
            "axisPlacement": "auto",
            "barAlignment": 0,
            "drawStyle": "line",
            "fillOpacity": 50,
            "gradientMode": "none",
            "hideFrom": {
              "legend": false,
              "tooltip": false,
              "viz": false
            },
            "lineInterpolation": "linear",
            "lineWidth": 1,
            "pointSize": 5,
            "scaleDistribution": {
              "type": "linear"
            },
            "showPoints": "never",
            "spanNulls": true,
            "stacking": {
              "group": "A",
              "mode": "none"
            },
            "thresholdsStyle": {
              "mode": "off"
            }
          },
          "mappings": [],
          "thresholds": {
            "mode": "absolute",
            "steps": [
              {
                "color": "green",
                "value": null
              },
              {
                "color": "red",
                "value": 80
              }
            ]
          },
          "unit": "short"
        },
        "overrides": []
      },
      "gridPos": {
        "h": 6,
        "w": 12,
        "x": 12,
        "y": 16
      },
      "id": 19,
      "options": {
        "legend": {
          "calcs": [],
          "displayMode": "list",
          "placement": "bottom"
        },
        "tooltip": {
          "mode": "single"
        }
      },
      "pluginVersion": "8.1.0",
      "targets": [
        {
          "exemplar": true,
          "expr": "wormhole_terra_fee_account_balance_lamports{instance=~\"$instance\"}",
          "interval": "",
          "legendFormat": "token - {{instance}}",
          "queryType": "randomWalk",
          "refId": "A"
        }
      ],
      "timeFrom": null,
      "timeShift": null,
      "title": "Terra Fee Payer Balance",
      "type": "timeseries"
    },
    {
      "datasource": "${DS_PROMETHEUS}",
      "fieldConfig": {
        "defaults": {
          "color": {
            "mode": "palette-classic"
          },
          "custom": {
            "axisLabel": "",
            "axisPlacement": "auto",
            "barAlignment": 0,
            "drawStyle": "line",
            "fillOpacity": 15,
            "gradientMode": "none",
            "hideFrom": {
              "legend": false,
              "tooltip": false,
              "viz": false
            },
            "lineInterpolation": "linear",
            "lineWidth": 1,
            "pointSize": 5,
            "scaleDistribution": {
              "type": "linear"
            },
            "showPoints": "never",
            "spanNulls": true,
            "stacking": {
              "group": "A",
              "mode": "none"
            },
            "thresholdsStyle": {
              "mode": "off"
            }
          },
          "mappings": [],
          "thresholds": {
            "mode": "absolute",
            "steps": [
              {
                "color": "green",
                "value": null
              },
              {
                "color": "red",
                "value": 80
              }
            ]
          },
          "unit": "short"
        },
        "overrides": []
      },
      "gridPos": {
        "h": 9,
        "w": 12,
        "x": 0,
        "y": 22
      },
      "id": 17,
      "options": {
        "legend": {
          "calcs": [],
          "displayMode": "list",
          "placement": "bottom"
        },
        "tooltip": {
          "mode": "multi"
        }
      },
      "pluginVersion": "8.1.0",
      "targets": [
        {
          "exemplar": true,
          "expr": "rate(wormhole_p2p_broadcast_messages_received_total{instance=~\"$instance\"}[$__rate_interval])",
          "interval": "",
          "legendFormat": "{{type}}  - {{instance}}",
          "queryType": "randomWalk",
          "refId": "A"
        }
      ],
      "timeFrom": null,
      "timeShift": null,
      "title": "P2P Messages Received/s",
      "type": "timeseries"
    },
    {
      "datasource": "${DS_PROMETHEUS}",
      "fieldConfig": {
        "defaults": {
          "color": {
            "mode": "palette-classic"
          },
          "custom": {
            "axisLabel": "",
            "axisPlacement": "auto",
            "barAlignment": 0,
            "drawStyle": "line",
            "fillOpacity": 10,
            "gradientMode": "none",
            "hideFrom": {
              "legend": false,
              "tooltip": false,
              "viz": false
            },
            "lineInterpolation": "linear",
            "lineWidth": 1,
            "pointSize": 5,
            "scaleDistribution": {
              "type": "linear"
            },
            "showPoints": "never",
            "spanNulls": true,
            "stacking": {
              "group": "A",
              "mode": "none"
            },
            "thresholdsStyle": {
              "mode": "off"
            }
          },
          "mappings": [],
          "thresholds": {
            "mode": "absolute",
            "steps": [
              {
                "color": "green",
                "value": null
              },
              {
                "color": "red",
                "value": 80
              }
            ]
          },
          "unit": "short"
        },
        "overrides": []
      },
      "gridPos": {
        "h": 9,
        "w": 12,
        "x": 12,
        "y": 22
      },
      "id": 18,
      "options": {
        "legend": {
          "calcs": [],
          "displayMode": "list",
          "placement": "bottom"
        },
        "tooltip": {
          "mode": "multi"
        }
      },
      "pluginVersion": "8.1.0",
      "targets": [
        {
          "exemplar": true,
          "expr": "rate(wormhole_eth_connection_errors_total{instance=~\"$instance\"}[$__rate_interval])",
          "interval": "",
          "legendFormat": "[Ethereum] {{reason}} - {{instance}}",
          "queryType": "randomWalk",
          "refId": "A"
        },
        {
          "exemplar": true,
          "expr": "rate(wormhole_solana_connection_errors_total{instance=~\"$instance\"}[$__rate_interval])",
          "interval": "",
          "legendFormat": "[Solana] {{reason}} - {{instance}}",
          "queryType": "randomWalk",
          "refId": "B"
        },
        {
          "exemplar": true,
          "expr": "rate(wormhole_terra_connection_errors_total{instance=~\"$instance\"}[$__rate_interval])",
          "interval": "",
          "legendFormat": "[Terra] {{ reason }} - {{instance}}",
          "queryType": "randomWalk",
          "refId": "C"
        }
      ],
      "timeFrom": null,
      "timeShift": null,
      "title": "Watcher Error Rate",
      "type": "timeseries"
    },
    {
      "datasource": "${DS_PROMETHEUS}",
      "fieldConfig": {
        "defaults": {
          "color": {
            "mode": "palette-classic"
          },
          "custom": {
            "axisLabel": "",
            "axisPlacement": "auto",
            "barAlignment": 0,
            "drawStyle": "line",
            "fillOpacity": 15,
            "gradientMode": "none",
            "hideFrom": {
              "legend": false,
              "tooltip": false,
              "viz": false
            },
            "lineInterpolation": "linear",
            "lineWidth": 1,
            "pointSize": 5,
            "scaleDistribution": {
              "type": "linear"
            },
            "showPoints": "never",
            "spanNulls": true,
            "stacking": {
              "group": "A",
              "mode": "none"
            },
            "thresholdsStyle": {
              "mode": "off"
            }
          },
          "mappings": [],
          "thresholds": {
            "mode": "absolute",
            "steps": [
              {
                "color": "green",
                "value": null
              },
              {
                "color": "red",
                "value": 80
              }
            ]
          },
          "unit": "short"
        },
        "overrides": []
      },
      "gridPos": {
        "h": 8,
        "w": 24,
        "x": 0,
        "y": 31
      },
      "id": 16,
      "options": {
        "legend": {
          "calcs": [
            "max"
          ],
          "displayMode": "table",
          "placement": "right"
        },
        "tooltip": {
          "mode": "single"
        }
      },
      "pluginVersion": "8.1.0",
      "targets": [
        {
          "exemplar": true,
          "expr": "increase(wormhole_observations_signed_by_guardian_total{instance=~\"$instance\"}[$__rate_interval])",
          "interval": "",
          "legendFormat": "{{ addr }} - {{instance}}",
          "queryType": "randomWalk",
          "refId": "A"
        }
      ],
      "timeFrom": null,
      "timeShift": null,
      "title": "Observations by Guardian",
      "type": "timeseries"
    },
    {
      "datasource": "${DS_PROMETHEUS}",
      "fieldConfig": {
        "defaults": {
          "color": {
            "mode": "palette-classic"
          },
          "custom": {
            "axisLabel": "",
            "axisPlacement": "auto",
            "barAlignment": 0,
            "drawStyle": "line",
            "fillOpacity": 15,
            "gradientMode": "none",
            "hideFrom": {
              "legend": false,
              "tooltip": false,
              "viz": false
            },
            "lineInterpolation": "linear",
            "lineWidth": 1,
            "pointSize": 5,
            "scaleDistribution": {
              "type": "linear"
            },
            "showPoints": "never",
            "spanNulls": true,
            "stacking": {
              "group": "A",
              "mode": "none"
            },
            "thresholdsStyle": {
              "mode": "off"
            }
          },
          "mappings": [],
          "thresholds": {
            "mode": "absolute",
            "steps": [
              {
                "color": "green",
                "value": null
              },
              {
                "color": "red",
                "value": 80
              }
            ]
          },
          "unit": "short"
        },
        "overrides": []
      },
      "gridPos": {
        "h": 8,
        "w": 24,
        "x": 0,
        "y": 39
      },
      "id": 10,
      "options": {
        "legend": {
          "calcs": [
            "max"
          ],
          "displayMode": "table",
          "placement": "right"
        },
        "tooltip": {
          "mode": "single"
        }
      },
      "pluginVersion": "8.1.0",
      "targets": [
        {
          "exemplar": true,
          "expr": "increase(wormhole_aggregation_state_settled_signatures_total{instance=~\"$instance\",status!=\"present\"}[$__rate_interval])",
          "interval": "",
          "legendFormat": "{{addr}} [from {{ origin }}]",
          "queryType": "randomWalk",
          "refId": "A"
        }
      ],
      "timeFrom": null,
      "timeShift": null,
      "title": "Missing Signatures",
      "type": "timeseries"
    },
    {
      "cards": {
        "cardPadding": null,
        "cardRound": null
      },
      "color": {
        "cardColor": "#b4ff00",
        "colorScale": "sqrt",
        "colorScheme": "interpolateTurbo",
        "exponent": 0.5,
        "mode": "spectrum"
      },
      "dataFormat": "timeseries",
      "datasource": "${DS_PROMETHEUS}",
      "gridPos": {
        "h": 8,
        "w": 8,
        "x": 0,
        "y": 47
      },
      "heatmap": {},
      "hideZeroBuckets": false,
      "highlightCards": true,
      "id": 12,
      "legend": {
        "show": false
      },
      "pluginVersion": "7.3.6",
      "reverseYBuckets": false,
      "targets": [
        {
          "exemplar": true,
          "expr": "sum(increase(wormhole_solana_query_latency_bucket{instance=~\"$instance\"}[$__interval])) by (le)",
          "interval": "",
          "legendFormat": "",
          "queryType": "randomWalk",
          "refId": "A"
        }
      ],
      "timeFrom": null,
      "timeShift": null,
      "title": "Solana Query Latency",
      "tooltip": {
        "show": true,
        "showHistogram": false
      },
      "type": "heatmap",
      "xAxis": {
        "show": true
      },
      "xBucketNumber": null,
      "xBucketSize": null,
      "yAxis": {
        "decimals": null,
        "format": "short",
        "logBase": 1,
        "max": null,
        "min": null,
        "show": true,
        "splitFactor": null
      },
      "yBucketBound": "auto",
      "yBucketNumber": null,
      "yBucketSize": null
    },
    {
      "cards": {
        "cardPadding": null,
        "cardRound": null
      },
      "color": {
        "cardColor": "#b4ff00",
        "colorScale": "sqrt",
        "colorScheme": "interpolateTurbo",
        "exponent": 0.5,
        "mode": "spectrum"
      },
      "dataFormat": "timeseries",
      "datasource": "${DS_PROMETHEUS}",
      "gridPos": {
        "h": 8,
        "w": 8,
        "x": 8,
        "y": 47
      },
      "heatmap": {},
      "hideZeroBuckets": false,
      "highlightCards": true,
      "id": 13,
      "legend": {
        "show": false
      },
      "pluginVersion": "7.3.6",
      "reverseYBuckets": false,
      "targets": [
        {
          "exemplar": true,
          "expr": "sum(increase(wormhole_eth_query_latency_bucket{instance=~\"$instance\"}[$__interval])) by (le)",
          "interval": "",
          "legendFormat": "",
          "queryType": "randomWalk",
          "refId": "A"
        }
      ],
      "timeFrom": null,
      "timeShift": null,
      "title": "Ethereum Query Latency",
      "tooltip": {
        "show": true,
        "showHistogram": false
      },
      "type": "heatmap",
      "xAxis": {
        "show": true
      },
      "xBucketNumber": null,
      "xBucketSize": null,
      "yAxis": {
        "decimals": null,
        "format": "short",
        "logBase": 1,
        "max": null,
        "min": null,
        "show": true,
        "splitFactor": null
      },
      "yBucketBound": "auto",
      "yBucketNumber": null,
      "yBucketSize": null
    },
    {
      "cards": {
        "cardPadding": null,
        "cardRound": null
      },
      "color": {
        "cardColor": "#b4ff00",
        "colorScale": "sqrt",
        "colorScheme": "interpolateTurbo",
        "exponent": 0.5,
        "mode": "spectrum"
      },
      "dataFormat": "timeseries",
      "datasource": "${DS_PROMETHEUS}",
      "gridPos": {
        "h": 8,
        "w": 8,
        "x": 16,
        "y": 47
      },
      "heatmap": {},
      "hideZeroBuckets": false,
      "highlightCards": true,
      "id": 15,
      "legend": {
        "show": false
      },
      "pluginVersion": "7.3.6",
      "reverseYBuckets": false,
      "targets": [
        {
          "exemplar": true,
          "expr": "sum(increase(wormhole_terra_query_latency_bucket{instance=~\"$instance\"}[$__interval])) by (le)",
          "interval": "",
          "legendFormat": "",
          "queryType": "randomWalk",
          "refId": "A"
        }
      ],
      "timeFrom": null,
      "timeShift": null,
      "title": "Terra Query Latency",
      "tooltip": {
        "show": true,
        "showHistogram": false
      },
      "type": "heatmap",
      "xAxis": {
        "show": true
      },
      "xBucketNumber": null,
      "xBucketSize": null,
      "yAxis": {
        "decimals": null,
        "format": "short",
        "logBase": 1,
        "max": null,
        "min": null,
        "show": true,
        "splitFactor": null
      },
      "yBucketBound": "auto",
      "yBucketNumber": null,
      "yBucketSize": null
    }
  ],
  "refresh": "",
  "schemaVersion": 30,
  "style": "dark",
  "tags": [],
  "templating": {
    "list": [
      {
        "allValue": null,
        "current": {},
        "datasource": "${DS_PROMETHEUS}",
        "definition": "label_values(wormhole_eth_current_height, instance)",
        "description": null,
        "error": null,
        "hide": 0,
        "includeAll": true,
        "label": "Instance",
        "multi": false,
        "name": "instance",
        "options": [],
        "query": {
          "query": "label_values(wormhole_eth_current_height, instance)",
          "refId": "Prometheus-instance-Variable-Query"
        },
        "refresh": 1,
        "regex": "",
        "skipUrlSync": false,
        "sort": 0,
        "tagValuesQuery": "",
        "tagsQuery": "",
        "type": "query",
        "useTags": false
      }
    ]
  },
  "time": {
    "from": "now-3h",
    "to": "now"
  },
  "timepicker": {},
  "timezone": "",
  "title": "Wormhole",
  "uid": "CVGqeaYMz",
  "version": 20
}
